setup.cfg
setup.py
lcogt_logging/__init__.py
lcogt_logging/lcogt_formatter.py
lcogt_logging.egg-info/PKG-INFO
lcogt_logging.egg-info/SOURCES.txt
lcogt_logging.egg-info/dependency_links.txt
lcogt_logging.egg-info/top_level.txt
test/test_lcogt_logging.py