Metadata-Version: 1.1
Name: lcogt-logging
Version: 0.3.2
Summary: Library for formatting python log calls according to
Home-page: https://github.com/LCOGT/lcogt_logging
Author: Austin Riba
Author-email: ariba@lcogt.net
License: UNKNOWN
Download-URL: https://github.com/LCOGT/lcogt_logging/archive/master.zip
Keywords: logging,lcogt
Platform: UNKNOWN
Classifier: Programming Language :: Python :: 2
Classifier: Programming Language :: Python :: 3
